{
  "directed": false,
  "multigraph": false,
  "graph": {
    "hyperedges": [
      {
        "id": "patient_registration_flow",
        "label": "Patient Registration Flow",
        "nodes": [
          "pendaftaran_index",
          "pendaftaran_menghubungiserver",
          "ticket_index"
        ],
        "relation": "form",
        "confidence": "INFERRED",
        "confidence_score": 0.95,
        "source_file": "pages/pendaftaran/index.html"
      },
      {
        "id": "user_profile_verification_flow",
        "label": "User Profile Verification Flow",
        "nodes": [
          "profil_index",
          "verifikasiemail_index",
          "verifikasinomor_index"
        ],
        "relation": "form",
        "confidence": "INFERRED",
        "confidence_score": 0.95,
        "source_file": "pages/profil/index.html"
      }
    ]
  },
  "nodes": [
    {
      "label": "notifikasi.js",
      "file_type": "code",
      "source_file": "pages/notifikasi/notifikasi.js",
      "source_location": "L1",
      "_origin": "ast",
      "id": "notifikasi_notifikasi",
      "community": 1,
      "norm_label": "notifikasi.js"
    },
    {
      "label": "notificationsData",
      "file_type": "code",
      "source_file": "pages/notifikasi/notifikasi.js",
      "source_location": "L2",
      "_origin": "ast",
      "id": "notifikasi_notifikasi_notificationsdata",
      "community": 1,
      "norm_label": "notificationsdata"
    },
    {
      "label": "setFilter()",
      "file_type": "code",
      "source_file": "pages/notifikasi/notifikasi.js",
      "source_location": "L196",
      "_origin": "ast",
      "id": "notifikasi_notifikasi_setfilter",
      "community": 1,
      "norm_label": "setfilter()"
    },
    {
      "label": "renderFilters()",
      "file_type": "code",
      "source_file": "pages/notifikasi/notifikasi.js",
      "source_location": "L217",
      "_origin": "ast",
      "id": "notifikasi_notifikasi_renderfilters",
      "community": 1,
      "norm_label": "renderfilters()"
    },
    {
      "label": "getFilteredNotifications()",
      "file_type": "code",
      "source_file": "pages/notifikasi/notifikasi.js",
      "source_location": "L238",
      "_origin": "ast",
      "id": "notifikasi_notifikasi_getfilterednotifications",
      "community": 1,
      "norm_label": "getfilterednotifications()"
    },
    {
      "label": "renderNotificationList()",
      "file_type": "code",
      "source_file": "pages/notifikasi/notifikasi.js",
      "source_location": "L248",
      "_origin": "ast",
      "id": "notifikasi_notifikasi_rendernotificationlist",
      "community": 1,
      "norm_label": "rendernotificationlist()"
    },
    {
      "label": "selectNotification()",
      "file_type": "code",
      "source_file": "pages/notifikasi/notifikasi.js",
      "source_location": "L310",
      "_origin": "ast",
      "id": "notifikasi_notifikasi_selectnotification",
      "community": 1,
      "norm_label": "selectnotification()"
    },
    {
      "label": "loadNotificationDetails()",
      "file_type": "code",
      "source_file": "pages/notifikasi/notifikasi.js",
      "source_location": "L347",
      "_origin": "ast",
      "id": "notifikasi_notifikasi_loadnotificationdetails",
      "community": 1,
      "norm_label": "loadnotificationdetails()"
    },
    {
      "label": "showEmptyDetails()",
      "file_type": "code",
      "source_file": "pages/notifikasi/notifikasi.js",
      "source_location": "L410",
      "_origin": "ast",
      "id": "notifikasi_notifikasi_showemptydetails",
      "community": 1,
      "norm_label": "showemptydetails()"
    },
    {
      "label": "markCurrentAsRead()",
      "file_type": "code",
      "source_file": "pages/notifikasi/notifikasi.js",
      "source_location": "L416",
      "_origin": "ast",
      "id": "notifikasi_notifikasi_markcurrentasread",
      "community": 1,
      "norm_label": "markcurrentasread()"
    },
    {
      "label": "deleteCurrentNotification()",
      "file_type": "code",
      "source_file": "pages/notifikasi/notifikasi.js",
      "source_location": "L427",
      "_origin": "ast",
      "id": "notifikasi_notifikasi_deletecurrentnotification",
      "community": 1,
      "norm_label": "deletecurrentnotification()"
    },
    {
      "label": "goBackToList()",
      "file_type": "code",
      "source_file": "pages/notifikasi/notifikasi.js",
      "source_location": "L446",
      "_origin": "ast",
      "id": "notifikasi_notifikasi_gobacktolist",
      "community": 1,
      "norm_label": "gobacktolist()"
    },
    {
      "label": "navbar.js",
      "file_type": "code",
      "source_file": "public/navbar.js",
      "source_location": "L1",
      "_origin": "ast",
      "id": "public_navbar",
      "community": 2,
      "norm_label": "navbar.js"
    },
    {
      "label": "initNavbar()",
      "file_type": "code",
      "source_file": "public/navbar.js",
      "source_location": "L2",
      "_origin": "ast",
      "id": "public_navbar_initnavbar",
      "community": 2,
      "norm_label": "initnavbar()"
    },
    {
      "label": "tailwind.config.js",
      "file_type": "code",
      "source_file": "tailwind.config.js",
      "source_location": "L1",
      "_origin": "ast",
      "id": "tailwind_config",
      "community": 16,
      "norm_label": "tailwind.config.js"
    },
    {
      "label": "settings.json",
      "file_type": "code",
      "source_file": ".vscode/settings.json",
      "source_location": null,
      "source_url": null,
      "captured_at": null,
      "author": null,
      "contributor": null,
      "id": "settings",
      "community": 15,
      "norm_label": "settings.json"
    },
    {
      "label": "Login Background Graphic",
      "file_type": "image",
      "source_file": "pages/daftar_login/asset/background.png",
      "source_location": null,
      "source_url": null,
      "captured_at": null,
      "author": null,
      "contributor": null,
      "id": "asset_background",
      "community": 7,
      "norm_label": "login background graphic"
    },
    {
      "label": "Image Asset: Contact Us.svg",
      "file_type": "image",
      "source_file": "pages/profil/assets/Contact Us.svg",
      "source_location": null,
      "source_url": null,
      "captured_at": null,
      "author": null,
      "contributor": null,
      "id": "assets_contact_us",
      "community": 3,
      "norm_label": "image asset: contact us.svg"
    },
    {
      "label": "Clinic Banner Image",
      "file_type": "image",
      "source_file": "pages/profil/assets/clinic_banner.png",
      "source_location": null,
      "source_url": null,
      "captured_at": null,
      "author": null,
      "contributor": null,
      "id": "assets_clinic_banner",
      "community": 3,
      "norm_label": "clinic banner image"
    },
    {
      "label": "Image Asset: contact_ahmad.png",
      "file_type": "image",
      "source_file": "pages/profil/assets/contact_ahmad.png",
      "source_location": null,
      "source_url": null,
      "captured_at": null,
      "author": null,
      "contributor": null,
      "id": "assets_contact_ahmad",
      "community": 8,
      "norm_label": "image asset: contact_ahmad.png"
    },
    {
      "label": "Contact Form Illustration",
      "file_type": "image",
      "source_file": "pages/profil/assets/contact_illustration.png",
      "source_location": null,
      "source_url": null,
      "captured_at": null,
      "author": null,
      "contributor": null,
      "id": "assets_contact_illustration",
      "community": 9,
      "norm_label": "contact form illustration"
    },
    {
      "label": "Image Asset: contact_siti.png",
      "file_type": "image",
      "source_file": "pages/profil/assets/contact_siti.png",
      "source_location": null,
      "source_url": null,
      "captured_at": null,
      "author": null,
      "contributor": null,
      "id": "assets_contact_siti",
      "community": 10,
      "norm_label": "image asset: contact_siti.png"
    },
    {
      "label": "Image Asset: files_and_doc.svg",
      "file_type": "image",
      "source_file": "pages/profil/assets/files_and_doc.svg",
      "source_location": null,
      "source_url": null,
      "captured_at": null,
      "author": null,
      "contributor": null,
      "id": "assets_files_and_doc",
      "community": 3,
      "norm_label": "image asset: files_and_doc.svg"
    },
    {
      "label": "User Profile Default Avatar",
      "file_type": "image",
      "source_file": "pages/profil/assets/profile_avatar.png",
      "source_location": null,
      "source_url": null,
      "captured_at": null,
      "author": null,
      "contributor": null,
      "id": "assets_profile_avatar",
      "community": 3,
      "norm_label": "user profile default avatar"
    },
    {
      "label": "Hospital Logo Asset",
      "file_type": "image",
      "source_file": "public/LOGO.svg",
      "source_location": null,
      "source_url": null,
      "captured_at": null,
      "author": null,
      "contributor": null,
      "id": "logo",
      "community": 2,
      "norm_label": "hospital logo asset"
    },
    {
      "label": "Image Asset: icon untuk verifikasi.svg",
      "file_type": "image",
      "source_file": "public/icon untuk verifikasi.svg",
      "source_location": null,
      "source_url": null,
      "captured_at": null,
      "author": null,
      "contributor": null,
      "id": "icon_untuk_verifikasi",
      "community": 4,
      "norm_label": "image asset: icon untuk verifikasi.svg"
    },
    {
      "label": "Hero Carousel Image 1",
      "file_type": "image",
      "source_file": "root images/carousel 1.png",
      "source_location": null,
      "source_url": null,
      "captured_at": null,
      "author": null,
      "contributor": null,
      "id": "carousel_1",
      "community": 0,
      "norm_label": "hero carousel image 1"
    },
    {
      "label": "Hero Carousel Image 2",
      "file_type": "image",
      "source_file": "root images/carousel 2.png",
      "source_location": null,
      "source_url": null,
      "captured_at": null,
      "author": null,
      "contributor": null,
      "id": "carousel_2",
      "community": 0,
      "norm_label": "hero carousel image 2"
    },
    {
      "label": "Hero Carousel Image 3",
      "file_type": "image",
      "source_file": "root images/carousel 3.png",
      "source_location": null,
      "source_url": null,
      "captured_at": null,
      "author": null,
      "contributor": null,
      "id": "carousel_3",
      "community": 0,
      "norm_label": "hero carousel image 3"
    },
    {
      "label": "Hero Carousel Image 4",
      "file_type": "image",
      "source_file": "root images/carousel 4.png",
      "source_location": null,
      "source_url": null,
      "captured_at": null,
      "author": null,
      "contributor": null,
      "id": "carousel_4",
      "community": 0,
      "norm_label": "hero carousel image 4"
    },
    {
      "label": "Hero Carousel Image 5",
      "file_type": "image",
      "source_file": "root images/carousel 5.png",
      "source_location": null,
      "source_url": null,
      "captured_at": null,
      "author": null,
      "contributor": null,
      "id": "carousel_5",
      "community": 0,
      "norm_label": "hero carousel image 5"
    },
    {
      "label": "Hero Carousel Image 6",
      "file_type": "image",
      "source_file": "root images/carousel 6.png",
      "source_location": null,
      "source_url": null,
      "captured_at": null,
      "author": null,
      "contributor": null,
      "id": "carousel_6",
      "community": 0,
      "norm_label": "hero carousel image 6"
    },
    {
      "label": "Image Asset: header images.png",
      "file_type": "image",
      "source_file": "root images/header images.png",
      "source_location": null,
      "source_url": null,
      "captured_at": null,
      "author": null,
      "contributor": null,
      "id": "header_images",
      "community": 0,
      "norm_label": "image asset: header images.png"
    },
    {
      "label": "Image Asset: pantauMoodAnda.png",
      "file_type": "image",
      "source_file": "root images/pantauMoodAnda.png",
      "source_location": null,
      "source_url": null,
      "captured_at": null,
      "author": null,
      "contributor": null,
      "id": "pantaumoodanda",
      "community": 0,
      "norm_label": "image asset: pantaumoodanda.png"
    },
    {
      "label": "graphify.md",
      "file_type": "document",
      "source_file": ".agents/rules/graphify.md",
      "source_location": null,
      "source_url": null,
      "captured_at": null,
      "author": null,
      "contributor": null,
      "id": "rules_graphify",
      "community": 14,
      "norm_label": "graphify.md"
    },
    {
      "label": "graphify.md",
      "file_type": "document",
      "source_file": ".agents/workflows/graphify.md",
      "source_location": null,
      "source_url": null,
      "captured_at": null,
      "author": null,
      "contributor": null,
      "id": "workflows_graphify",
      "community": 17,
      "norm_label": "graphify.md"
    },
    {
      "label": "YOU'R TASK",
      "file_type": "document",
      "source_file": "AGENTS.md",
      "source_location": null,
      "source_url": null,
      "captured_at": null,
      "author": null,
      "contributor": null,
      "id": "agents",
      "community": 6,
      "norm_label": "you'r task"
    },
    {
      "label": "\ud83d\udcc1 Panduan Struktur Proyek & Git",
      "file_type": "document",
      "source_file": "Readme.md",
      "source_location": null,
      "source_url": null,
      "captured_at": null,
      "author": null,
      "contributor": null,
      "id": "readme",
      "community": 13,
      "norm_label": "\ud83d\udcc1 panduan struktur proyek & git"
    },
    {
      "label": "contohparams.txt",
      "file_type": "document",
      "source_file": "contohparams.txt",
      "source_location": null,
      "source_url": null,
      "captured_at": null,
      "author": null,
      "contributor": null,
      "id": "contohparams",
      "community": 11,
      "norm_label": "contohparams.txt"
    },
    {
      "label": "HealthFlow Clinic",
      "file_type": "document",
      "source_file": "index.html",
      "source_location": null,
      "source_url": null,
      "captured_at": null,
      "author": null,
      "contributor": null,
      "id": "index",
      "community": 0,
      "norm_label": "healthflow clinic"
    },
    {
      "label": "global.css",
      "file_type": "document",
      "source_file": "public/global.css",
      "source_location": null,
      "source_url": null,
      "captured_at": null,
      "author": null,
      "contributor": null,
      "id": "global",
      "community": 4,
      "norm_label": "global.css"
    },
    {
      "label": "HealthFlow Clinic",
      "file_type": "document",
      "source_file": "index_notLogin.html",
      "source_location": null,
      "source_url": null,
      "captured_at": null,
      "author": null,
      "contributor": null,
      "id": "index_notlogin",
      "community": 0,
      "norm_label": "healthflow clinic"
    },
    {
      "label": "Pendaftaran Pasien - HealthFlow Clinic",
      "file_type": "document",
      "source_file": "pages/daftar_login/index.html",
      "source_location": null,
      "source_url": null,
      "captured_at": null,
      "author": null,
      "contributor": null,
      "id": "daftar_login_index",
      "community": 0,
      "norm_label": "pendaftaran pasien - healthflow clinic"
    },
    {
      "label": "daftar.css",
      "file_type": "document",
      "source_file": "pages/daftar_login/daftar.css",
      "source_location": null,
      "source_url": null,
      "captured_at": null,
      "author": null,
      "contributor": null,
      "id": "daftar_login_daftar",
      "community": 0,
      "norm_label": "daftar.css"
    },
    {
      "label": "hi.txt",
      "file_type": "document",
      "source_file": "pages/hi.txt",
      "source_location": null,
      "source_url": null,
      "captured_at": null,
      "author": null,
      "contributor": null,
      "id": "hi",
      "community": 12,
      "norm_label": "hi.txt"
    },
    {
      "label": "Lokasi Klinik",
      "file_type": "document",
      "source_file": "pages/lokasi/index.html",
      "source_location": null,
      "source_url": null,
      "captured_at": null,
      "author": null,
      "contributor": null,
      "id": "lokasi_index",
      "community": 2,
      "norm_label": "lokasi klinik"
    },
    {
      "label": "PendaftaranPasienBaru.css",
      "file_type": "document",
      "source_file": "pages/pendaftaran/PendaftaranPasienBaru.css",
      "source_location": null,
      "source_url": null,
      "captured_at": null,
      "author": null,
      "contributor": null,
      "id": "pendaftaran_pendaftaranpasienbaru",
      "community": 4,
      "norm_label": "pendaftaranpasienbaru.css"
    },
    {
      "label": "Notifikasi - HealthFlow Clinic",
      "file_type": "document",
      "source_file": "pages/notifikasi/index.html",
      "source_location": null,
      "source_url": null,
      "captured_at": null,
      "author": null,
      "contributor": null,
      "id": "notifikasi_index",
      "community": 2,
      "norm_label": "notifikasi - healthflow clinic"
    },
    {
      "label": "Pendaftaran",
      "file_type": "document",
      "source_file": "pages/pendaftaran/index.html",
      "source_location": null,
      "source_url": null,
      "captured_at": null,
      "author": null,
      "contributor": null,
      "id": "pendaftaran_index",
      "community": 2,
      "norm_label": "pendaftaran"
    },
    {
      "label": "Document",
      "file_type": "document",
      "source_file": "pages/pendaftaran/menghubungiServer.html",
      "source_location": null,
      "source_url": null,
      "captured_at": null,
      "author": null,
      "contributor": null,
      "id": "pendaftaran_menghubungiserver",
      "community": 4,
      "norm_label": "document"
    },
    {
      "label": "Tiket Reservasi - HealthFlow",
      "file_type": "document",
      "source_file": "pages/pendaftaran/ticket/index.html",
      "source_location": null,
      "source_url": null,
      "captured_at": null,
      "author": null,
      "contributor": null,
      "id": "ticket_index",
      "community": 2,
      "norm_label": "tiket reservasi - healthflow"
    },
    {
      "label": "Profil Pasien",
      "file_type": "document",
      "source_file": "pages/profil/index.html",
      "source_location": null,
      "source_url": null,
      "captured_at": null,
      "author": null,
      "contributor": null,
      "id": "profil_index",
      "community": 3,
      "norm_label": "profil pasien"
    },
    {
      "label": "profil.css",
      "file_type": "document",
      "source_file": "pages/profil/profil.css",
      "source_location": null,
      "source_url": null,
      "captured_at": null,
      "author": null,
      "contributor": null,
      "id": "profil_profil",
      "community": 3,
      "norm_label": "profil.css"
    },
    {
      "label": "Ubah Email - HealthFlow",
      "file_type": "document",
      "source_file": "pages/profil/verifikasiEmail/index.html",
      "source_location": null,
      "source_url": null,
      "captured_at": null,
      "author": null,
      "contributor": null,
      "id": "verifikasiemail_index",
      "community": 4,
      "norm_label": "ubah email - healthflow"
    },
    {
      "label": "Ubah Nomor Telepon - HealthFlow",
      "file_type": "document",
      "source_file": "pages/profil/verifikasiNomor/index.html",
      "source_location": null,
      "source_url": null,
      "captured_at": null,
      "author": null,
      "contributor": null,
      "id": "verifikasinomor_index",
      "community": 4,
      "norm_label": "ubah nomor telepon - healthflow"
    },
    {
      "label": "Rekam Medis Pasien",
      "file_type": "document",
      "source_file": "pages/rekam_medis/index.html",
      "source_location": null,
      "source_url": null,
      "captured_at": null,
      "author": null,
      "contributor": null,
      "id": "rekam_medis_index",
      "community": 5,
      "norm_label": "rekam medis pasien"
    },
    {
      "label": "rekam_medis.css",
      "file_type": "document",
      "source_file": "pages/rekam_medis/rekam_medis.css",
      "source_location": null,
      "source_url": null,
      "captured_at": null,
      "author": null,
      "contributor": null,
      "id": "rekam_medis_rekam_medis",
      "community": 5,
      "norm_label": "rekam_medis.css"
    }
  ],
  "links": [
    {
      "relation": "references",
      "confidence": "EXTRACTED",
      "confidence_score": 1.0,
      "source_file": "pages/notifikasi/index.html",
      "source_location": null,
      "weight": 1.0,
      "source": "notifikasi_index",
      "target": "notifikasi_notifikasi"
    },
    {
      "relation": "contains",
      "confidence": "EXTRACTED",
      "source_file": "pages/notifikasi/notifikasi.js",
      "source_location": "L427",
      "weight": 1.0,
      "source": "notifikasi_notifikasi",
      "target": "notifikasi_notifikasi_deletecurrentnotification",
      "confidence_score": 1.0
    },
    {
      "relation": "contains",
      "confidence": "EXTRACTED",
      "source_file": "pages/notifikasi/notifikasi.js",
      "source_location": "L238",
      "weight": 1.0,
      "source": "notifikasi_notifikasi",
      "target": "notifikasi_notifikasi_getfilterednotifications",
      "confidence_score": 1.0
    },
    {
      "relation": "contains",
      "confidence": "EXTRACTED",
      "source_file": "pages/notifikasi/notifikasi.js",
      "source_location": "L446",
      "weight": 1.0,
      "source": "notifikasi_notifikasi",
      "target": "notifikasi_notifikasi_gobacktolist",
      "confidence_score": 1.0
    },
    {
      "relation": "contains",
      "confidence": "EXTRACTED",
      "source_file": "pages/notifikasi/notifikasi.js",
      "source_location": "L347",
      "weight": 1.0,
      "source": "notifikasi_notifikasi",
      "target": "notifikasi_notifikasi_loadnotificationdetails",
      "confidence_score": 1.0
    },
    {
      "relation": "contains",
      "confidence": "EXTRACTED",
      "source_file": "pages/notifikasi/notifikasi.js",
      "source_location": "L416",
      "weight": 1.0,
      "source": "notifikasi_notifikasi",
      "target": "notifikasi_notifikasi_markcurrentasread",
      "confidence_score": 1.0
    },
    {
      "relation": "contains",
      "confidence": "EXTRACTED",
      "source_file": "pages/notifikasi/notifikasi.js",
      "source_location": "L2",
      "weight": 1.0,
      "source": "notifikasi_notifikasi",
      "target": "notifikasi_notifikasi_notificationsdata",
      "confidence_score": 1.0
    },
    {
      "relation": "contains",
      "confidence": "EXTRACTED",
      "source_file": "pages/notifikasi/notifikasi.js",
      "source_location": "L217",
      "weight": 1.0,
      "source": "notifikasi_notifikasi",
      "target": "notifikasi_notifikasi_renderfilters",
      "confidence_score": 1.0
    },
    {
      "relation": "contains",
      "confidence": "EXTRACTED",
      "source_file": "pages/notifikasi/notifikasi.js",
      "source_location": "L248",
      "weight": 1.0,
      "source": "notifikasi_notifikasi",
      "target": "notifikasi_notifikasi_rendernotificationlist",
      "confidence_score": 1.0
    },
    {
      "relation": "contains",
      "confidence": "EXTRACTED",
      "source_file": "pages/notifikasi/notifikasi.js",
      "source_location": "L310",
      "weight": 1.0,
      "source": "notifikasi_notifikasi",
      "target": "notifikasi_notifikasi_selectnotification",
      "confidence_score": 1.0
    },
    {
      "relation": "contains",
      "confidence": "EXTRACTED",
      "source_file": "pages/notifikasi/notifikasi.js",
      "source_location": "L196",
      "weight": 1.0,
      "source": "notifikasi_notifikasi",
      "target": "notifikasi_notifikasi_setfilter",
      "confidence_score": 1.0
    },
    {
      "relation": "contains",
      "confidence": "EXTRACTED",
      "source_file": "pages/notifikasi/notifikasi.js",
      "source_location": "L410",
      "weight": 1.0,
      "source": "notifikasi_notifikasi",
      "target": "notifikasi_notifikasi_showemptydetails",
      "confidence_score": 1.0
    },
    {
      "relation": "calls",
      "context": "call",
      "confidence": "EXTRACTED",
      "source_file": "pages/notifikasi/notifikasi.js",
      "source_location": "L202",
      "weight": 1.0,
      "source": "notifikasi_notifikasi_setfilter",
      "target": "notifikasi_notifikasi_getfilterednotifications",
      "confidence_score": 1.0
    },
    {
      "relation": "calls",
      "context": "call",
      "confidence": "EXTRACTED",
      "source_file": "pages/notifikasi/notifikasi.js",
      "source_location": "L209",
      "weight": 1.0,
      "source": "notifikasi_notifikasi_setfilter",
      "target": "notifikasi_notifikasi_loadnotificationdetails",
      "confidence_score": 1.0
    },
    {
      "relation": "calls",
      "context": "call",
      "confidence": "EXTRACTED",
      "source_file": "pages/notifikasi/notifikasi.js",
      "source_location": "L198",
      "weight": 1.0,
      "source": "notifikasi_notifikasi_setfilter",
      "target": "notifikasi_notifikasi_renderfilters",
      "confidence_score": 1.0
    },
    {
      "relation": "calls",
      "context": "call",
      "confidence": "EXTRACTED",
      "source_file": "pages/notifikasi/notifikasi.js",
      "source_location": "L199",
      "weight": 1.0,
      "source": "notifikasi_notifikasi_setfilter",
      "target": "notifikasi_notifikasi_rendernotificationlist",
      "confidence_score": 1.0
    },
    {
      "relation": "calls",
      "context": "call",
      "confidence": "EXTRACTED",
      "source_file": "pages/notifikasi/notifikasi.js",
      "source_location": "L212",
      "weight": 1.0,
      "source": "notifikasi_notifikasi_setfilter",
      "target": "notifikasi_notifikasi_showemptydetails",
      "confidence_score": 1.0
    },
    {
      "relation": "calls",
      "context": "call",
      "confidence": "EXTRACTED",
      "source_file": "pages/notifikasi/notifikasi.js",
      "source_location": "L421",
      "weight": 1.0,
      "source": "notifikasi_notifikasi_markcurrentasread",
      "target": "notifikasi_notifikasi_renderfilters",
      "confidence_score": 1.0
    },
    {
      "relation": "calls",
      "context": "call",
      "confidence": "EXTRACTED",
      "source_file": "pages/notifikasi/notifikasi.js",
      "source_location": "L334",
      "weight": 1.0,
      "source": "notifikasi_notifikasi_selectnotification",
      "target": "notifikasi_notifikasi_renderfilters",
      "confidence_score": 1.0
    },
    {
      "relation": "calls",
      "context": "call",
      "confidence": "EXTRACTED",
      "source_file": "pages/notifikasi/notifikasi.js",
      "source_location": "L433",
      "weight": 1.0,
      "source": "notifikasi_notifikasi_deletecurrentnotification",
      "target": "notifikasi_notifikasi_getfilterednotifications",
      "confidence_score": 1.0
    },
    {
      "relation": "calls",
      "context": "call",
      "confidence": "EXTRACTED",
      "source_file": "pages/notifikasi/notifikasi.js",
      "source_location": "L252",
      "weight": 1.0,
      "source": "notifikasi_notifikasi_rendernotificationlist",
      "target": "notifikasi_notifikasi_getfilterednotifications",
      "confidence_score": 1.0
    },
    {
      "relation": "calls",
      "context": "call",
      "confidence": "EXTRACTED",
      "source_file": "pages/notifikasi/notifikasi.js",
      "source_location": "L442",
      "weight": 1.0,
      "source": "notifikasi_notifikasi_deletecurrentnotification",
      "target": "notifikasi_notifikasi_rendernotificationlist",
      "confidence_score": 1.0
    },
    {
      "relation": "calls",
      "context": "call",
      "confidence": "EXTRACTED",
      "source_file": "pages/notifikasi/notifikasi.js",
      "source_location": "L420",
      "weight": 1.0,
      "source": "notifikasi_notifikasi_markcurrentasread",
      "target": "notifikasi_notifikasi_rendernotificationlist",
      "confidence_score": 1.0
    },
    {
      "relation": "calls",
      "context": "call",
      "confidence": "EXTRACTED",
      "source_file": "pages/notifikasi/notifikasi.js",
      "source_location": "L333",
      "weight": 1.0,
      "source": "notifikasi_notifikasi_selectnotification",
      "target": "notifikasi_notifikasi_rendernotificationlist",
      "confidence_score": 1.0
    },
    {
      "relation": "calls",
      "context": "call",
      "confidence": "EXTRACTED",
      "source_file": "pages/notifikasi/notifikasi.js",
      "source_location": "L327",
      "weight": 1.0,
      "source": "notifikasi_notifikasi_selectnotification",
      "target": "notifikasi_notifikasi_loadnotificationdetails",
      "confidence_score": 1.0
    },
    {
      "relation": "calls",
      "context": "call",
      "confidence": "EXTRACTED",
      "source_file": "pages/notifikasi/notifikasi.js",
      "source_location": "L436",
      "weight": 1.0,
      "source": "notifikasi_notifikasi_deletecurrentnotification",
      "target": "notifikasi_notifikasi_loadnotificationdetails",
      "confidence_score": 1.0
    },
    {
      "relation": "calls",
      "context": "call",
      "confidence": "EXTRACTED",
      "source_file": "pages/notifikasi/notifikasi.js",
      "source_location": "L354",
      "weight": 1.0,
      "source": "notifikasi_notifikasi_loadnotificationdetails",
      "target": "notifikasi_notifikasi_showemptydetails",
      "confidence_score": 1.0
    },
    {
      "relation": "calls",
      "context": "call",
      "confidence": "EXTRACTED",
      "source_file": "pages/notifikasi/notifikasi.js",
      "source_location": "L422",
      "weight": 1.0,
      "source": "notifikasi_notifikasi_markcurrentasread",
      "target": "notifikasi_notifikasi_loadnotificationdetails",
      "confidence_score": 1.0
    },
    {
      "relation": "calls",
      "context": "call",
      "confidence": "EXTRACTED",
      "source_file": "pages/notifikasi/notifikasi.js",
      "source_location": "L439",
      "weight": 1.0,
      "source": "notifikasi_notifikasi_deletecurrentnotification",
      "target": "notifikasi_notifikasi_showemptydetails",
      "confidence_score": 1.0
    },
    {
      "relation": "references",
      "confidence": "EXTRACTED",
      "confidence_score": 1.0,
      "source_file": "index.html",
      "source_location": null,
      "weight": 1.0,
      "source": "index",
      "target": "public_navbar"
    },
    {
      "relation": "references",
      "confidence": "EXTRACTED",
      "confidence_score": 1.0,
      "source_file": "index_notLogin.html",
      "source_location": null,
      "weight": 1.0,
      "source": "index_notlogin",
      "target": "public_navbar"
    },
    {
      "relation": "references",
      "confidence": "EXTRACTED",
      "confidence_score": 1.0,
      "source_file": "pages/lokasi/index.html",
      "source_location": null,
      "weight": 1.0,
      "source": "lokasi_index",
      "target": "public_navbar"
    },
    {
      "relation": "references",
      "confidence": "EXTRACTED",
      "confidence_score": 1.0,
      "source_file": "pages/notifikasi/index.html",
      "source_location": null,
      "weight": 1.0,
      "source": "notifikasi_index",
      "target": "public_navbar"
    },
    {
      "relation": "references",
      "confidence": "EXTRACTED",
      "confidence_score": 1.0,
      "source_file": "pages/pendaftaran/index.html",
      "source_location": null,
      "weight": 1.0,
      "source": "pendaftaran_index",
      "target": "public_navbar"
    },
    {
      "relation": "references",
      "confidence": "EXTRACTED",
      "confidence_score": 1.0,
      "source_file": "pages/profil/index.html",
      "source_location": null,
      "weight": 1.0,
      "source": "profil_index",
      "target": "public_navbar"
    },
    {
      "relation": "contains",
      "confidence": "EXTRACTED",
      "source_file": "public/navbar.js",
      "source_location": "L2",
      "weight": 1.0,
      "source": "public_navbar",
      "target": "public_navbar_initnavbar",
      "confidence_score": 1.0
    },
    {
      "relation": "references",
      "confidence": "EXTRACTED",
      "confidence_score": 1.0,
      "source_file": "pages/rekam_medis/index.html",
      "source_location": null,
      "weight": 1.0,
      "source": "rekam_medis_index",
      "target": "public_navbar"
    },
    {
      "relation": "references",
      "confidence": "EXTRACTED",
      "confidence_score": 1.0,
      "source_file": "pages/pendaftaran/ticket/index.html",
      "source_location": null,
      "weight": 1.0,
      "source": "ticket_index",
      "target": "public_navbar"
    },
    {
      "relation": "references",
      "confidence": "EXTRACTED",
      "confidence_score": 1.0,
      "source_file": "pages/profil/verifikasiEmail/index.html",
      "source_location": null,
      "weight": 1.0,
      "source": "verifikasiemail_index",
      "target": "public_navbar"
    },
    {
      "relation": "references",
      "confidence": "EXTRACTED",
      "confidence_score": 1.0,
      "source_file": "pages/profil/verifikasiNomor/index.html",
      "source_location": null,
      "weight": 1.0,
      "source": "verifikasinomor_index",
      "target": "public_navbar"
    },
    {
      "relation": "references",
      "confidence": "EXTRACTED",
      "confidence_score": 1.0,
      "source_file": "pages/profil/index.html",
      "source_location": null,
      "weight": 1.0,
      "source": "profil_index",
      "target": "assets_contact_us"
    },
    {
      "relation": "references",
      "confidence": "EXTRACTED",
      "confidence_score": 1.0,
      "source_file": "pages/profil/index.html",
      "source_location": null,
      "weight": 1.0,
      "source": "profil_index",
      "target": "assets_clinic_banner"
    },
    {
      "relation": "references",
      "confidence": "EXTRACTED",
      "confidence_score": 1.0,
      "source_file": "pages/profil/index.html",
      "source_location": null,
      "weight": 1.0,
      "source": "profil_index",
      "target": "assets_files_and_doc"
    },
    {
      "relation": "references",
      "confidence": "EXTRACTED",
      "confidence_score": 1.0,
      "source_file": "index.html",
      "source_location": null,
      "weight": 1.0,
      "source": "index",
      "target": "assets_profile_avatar"
    },
    {
      "relation": "references",
      "confidence": "EXTRACTED",
      "confidence_score": 1.0,
      "source_file": "pages/profil/index.html",
      "source_location": null,
      "weight": 1.0,
      "source": "profil_index",
      "target": "assets_profile_avatar"
    },
    {
      "relation": "references",
      "confidence": "EXTRACTED",
      "confidence_score": 1.0,
      "source_file": "pages/daftar_login/index.html",
      "source_location": null,
      "weight": 1.0,
      "source": "daftar_login_index",
      "target": "logo"
    },
    {
      "relation": "references",
      "confidence": "EXTRACTED",
      "confidence_score": 1.0,
      "source_file": "index.html",
      "source_location": null,
      "weight": 1.0,
      "source": "index",
      "target": "logo"
    },
    {
      "relation": "references",
      "confidence": "EXTRACTED",
      "confidence_score": 1.0,
      "source_file": "index_notLogin.html",
      "source_location": null,
      "weight": 1.0,
      "source": "index_notlogin",
      "target": "logo"
    },
    {
      "relation": "references",
      "confidence": "EXTRACTED",
      "confidence_score": 1.0,
      "source_file": "pages/lokasi/index.html",
      "source_location": null,
      "weight": 1.0,
      "source": "lokasi_index",
      "target": "logo"
    },
    {
      "relation": "references",
      "confidence": "EXTRACTED",
      "confidence_score": 1.0,
      "source_file": "pages/notifikasi/index.html",
      "source_location": null,
      "weight": 1.0,
      "source": "notifikasi_index",
      "target": "logo"
    },
    {
      "relation": "references",
      "confidence": "EXTRACTED",
      "confidence_score": 1.0,
      "source_file": "pages/pendaftaran/index.html",
      "source_location": null,
      "weight": 1.0,
      "source": "pendaftaran_index",
      "target": "logo"
    },
    {
      "relation": "references",
      "confidence": "EXTRACTED",
      "confidence_score": 1.0,
      "source_file": "pages/profil/index.html",
      "source_location": null,
      "weight": 1.0,
      "source": "profil_index",
      "target": "logo"
    },
    {
      "relation": "references",
      "confidence": "EXTRACTED",
      "confidence_score": 1.0,
      "source_file": "pages/rekam_medis/index.html",
      "source_location": null,
      "weight": 1.0,
      "source": "rekam_medis_index",
      "target": "logo"
    },
    {
      "relation": "references",
      "confidence": "EXTRACTED",
      "confidence_score": 1.0,
      "source_file": "pages/pendaftaran/ticket/index.html",
      "source_location": null,
      "weight": 1.0,
      "source": "ticket_index",
      "target": "logo"
    },
    {
      "relation": "references",
      "confidence": "EXTRACTED",
      "confidence_score": 1.0,
      "source_file": "pages/profil/verifikasiEmail/index.html",
      "source_location": null,
      "weight": 1.0,
      "source": "verifikasiemail_index",
      "target": "logo"
    },
    {
      "relation": "references",
      "confidence": "EXTRACTED",
      "confidence_score": 1.0,
      "source_file": "pages/profil/verifikasiNomor/index.html",
      "source_location": null,
      "weight": 1.0,
      "source": "verifikasinomor_index",
      "target": "logo"
    },
    {
      "relation": "references",
      "confidence": "EXTRACTED",
      "confidence_score": 1.0,
      "source_file": "pages/profil/verifikasiEmail/index.html",
      "source_location": null,
      "weight": 1.0,
      "source": "verifikasiemail_index",
      "target": "icon_untuk_verifikasi"
    },
    {
      "relation": "references",
      "confidence": "EXTRACTED",
      "confidence_score": 1.0,
      "source_file": "pages/profil/verifikasiNomor/index.html",
      "source_location": null,
      "weight": 1.0,
      "source": "verifikasinomor_index",
      "target": "icon_untuk_verifikasi"
    },
    {
      "relation": "references",
      "confidence": "EXTRACTED",
      "confidence_score": 1.0,
      "source_file": "index.html",
      "source_location": null,
      "weight": 1.0,
      "source": "index",
      "target": "carousel_1"
    },
    {
      "relation": "references",
      "confidence": "EXTRACTED",
      "confidence_score": 1.0,
      "source_file": "index_notLogin.html",
      "source_location": null,
      "weight": 1.0,
      "source": "index_notlogin",
      "target": "carousel_1"
    },
    {
      "relation": "references",
      "confidence": "EXTRACTED",
      "confidence_score": 1.0,
      "source_file": "index.html",
      "source_location": null,
      "weight": 1.0,
      "source": "index",
      "target": "carousel_2"
    },
    {
      "relation": "references",
      "confidence": "EXTRACTED",
      "confidence_score": 1.0,
      "source_file": "index_notLogin.html",
      "source_location": null,
      "weight": 1.0,
      "source": "index_notlogin",
      "target": "carousel_2"
    },
    {
      "relation": "references",
      "confidence": "EXTRACTED",
      "confidence_score": 1.0,
      "source_file": "index.html",
      "source_location": null,
      "weight": 1.0,
      "source": "index",
      "target": "carousel_3"
    },
    {
      "relation": "references",
      "confidence": "EXTRACTED",
      "confidence_score": 1.0,
      "source_file": "index_notLogin.html",
      "source_location": null,
      "weight": 1.0,
      "source": "index_notlogin",
      "target": "carousel_3"
    },
    {
      "relation": "references",
      "confidence": "EXTRACTED",
      "confidence_score": 1.0,
      "source_file": "index.html",
      "source_location": null,
      "weight": 1.0,
      "source": "index",
      "target": "carousel_4"
    },
    {
      "relation": "references",
      "confidence": "EXTRACTED",
      "confidence_score": 1.0,
      "source_file": "index_notLogin.html",
      "source_location": null,
      "weight": 1.0,
      "source": "index_notlogin",
      "target": "carousel_4"
    },
    {
      "relation": "references",
      "confidence": "EXTRACTED",
      "confidence_score": 1.0,
      "source_file": "index.html",
      "source_location": null,
      "weight": 1.0,
      "source": "index",
      "target": "carousel_5"
    },
    {
      "relation": "references",
      "confidence": "EXTRACTED",
      "confidence_score": 1.0,
      "source_file": "index_notLogin.html",
      "source_location": null,
      "weight": 1.0,
      "source": "index_notlogin",
      "target": "carousel_5"
    },
    {
      "relation": "references",
      "confidence": "EXTRACTED",
      "confidence_score": 1.0,
      "source_file": "index.html",
      "source_location": null,
      "weight": 1.0,
      "source": "index",
      "target": "carousel_6"
    },
    {
      "relation": "references",
      "confidence": "EXTRACTED",
      "confidence_score": 1.0,
      "source_file": "index_notLogin.html",
      "source_location": null,
      "weight": 1.0,
      "source": "index_notlogin",
      "target": "carousel_6"
    },
    {
      "relation": "references",
      "confidence": "EXTRACTED",
      "confidence_score": 1.0,
      "source_file": "index.html",
      "source_location": null,
      "weight": 1.0,
      "source": "index",
      "target": "header_images"
    },
    {
      "relation": "references",
      "confidence": "EXTRACTED",
      "confidence_score": 1.0,
      "source_file": "index_notLogin.html",
      "source_location": null,
      "weight": 1.0,
      "source": "index_notlogin",
      "target": "header_images"
    },
    {
      "relation": "references",
      "confidence": "EXTRACTED",
      "confidence_score": 1.0,
      "source_file": "index.html",
      "source_location": null,
      "weight": 1.0,
      "source": "index",
      "target": "pantaumoodanda"
    },
    {
      "relation": "references",
      "confidence": "EXTRACTED",
      "confidence_score": 1.0,
      "source_file": "index_notLogin.html",
      "source_location": null,
      "weight": 1.0,
      "source": "index_notlogin",
      "target": "pantaumoodanda"
    },
    {
      "relation": "references",
      "confidence": "EXTRACTED",
      "confidence_score": 1.0,
      "source_file": "pages/daftar_login/index.html",
      "source_location": null,
      "weight": 1.0,
      "source": "daftar_login_index",
      "target": "index"
    },
    {
      "relation": "references",
      "confidence": "EXTRACTED",
      "confidence_score": 1.0,
      "source_file": "index.html",
      "source_location": null,
      "weight": 1.0,
      "source": "index",
      "target": "global"
    },
    {
      "relation": "references",
      "confidence": "EXTRACTED",
      "confidence_score": 1.0,
      "source_file": "index.html",
      "source_location": null,
      "weight": 1.0,
      "source": "index",
      "target": "index"
    },
    {
      "relation": "references",
      "confidence": "EXTRACTED",
      "confidence_score": 1.0,
      "source_file": "index_notLogin.html",
      "source_location": null,
      "weight": 1.0,
      "source": "index_notlogin",
      "target": "index"
    },
    {
      "relation": "references",
      "confidence": "EXTRACTED",
      "confidence_score": 1.0,
      "source_file": "index.html",
      "source_location": null,
      "weight": 1.0,
      "source": "index",
      "target": "profil_index"
    },
    {
      "relation": "references",
      "confidence": "EXTRACTED",
      "confidence_score": 1.0,
      "source_file": "pages/lokasi/index.html",
      "source_location": null,
      "weight": 1.0,
      "source": "lokasi_index",
      "target": "index"
    },
    {
      "relation": "references",
      "confidence": "EXTRACTED",
      "confidence_score": 1.0,
      "source_file": "pages/notifikasi/index.html",
      "source_location": null,
      "weight": 1.0,
      "source": "notifikasi_index",
      "target": "index"
    },
    {
      "relation": "references",
      "confidence": "EXTRACTED",
      "confidence_score": 1.0,
      "source_file": "pages/pendaftaran/index.html",
      "source_location": null,
      "weight": 1.0,
      "source": "pendaftaran_index",
      "target": "index"
    },
    {
      "relation": "references",
      "confidence": "EXTRACTED",
      "confidence_score": 1.0,
      "source_file": "pages/rekam_medis/index.html",
      "source_location": null,
      "weight": 1.0,
      "source": "rekam_medis_index",
      "target": "index"
    },
    {
      "relation": "references",
      "confidence": "EXTRACTED",
      "confidence_score": 1.0,
      "source_file": "pages/pendaftaran/ticket/index.html",
      "source_location": null,
      "weight": 1.0,
      "source": "ticket_index",
      "target": "index"
    },
    {
      "relation": "references",
      "confidence": "EXTRACTED",
      "confidence_score": 1.0,
      "source_file": "pages/profil/verifikasiEmail/index.html",
      "source_location": null,
      "weight": 1.0,
      "source": "verifikasiemail_index",
      "target": "index"
    },
    {
      "relation": "references",
      "confidence": "EXTRACTED",
      "confidence_score": 1.0,
      "source_file": "pages/profil/verifikasiNomor/index.html",
      "source_location": null,
      "weight": 1.0,
      "source": "verifikasinomor_index",
      "target": "index"
    },
    {
      "relation": "references",
      "confidence": "EXTRACTED",
      "confidence_score": 1.0,
      "source_file": "pages/daftar_login/index.html",
      "source_location": null,
      "weight": 1.0,
      "source": "daftar_login_index",
      "target": "global"
    },
    {
      "relation": "references",
      "confidence": "EXTRACTED",
      "confidence_score": 1.0,
      "source_file": "index_notLogin.html",
      "source_location": null,
      "weight": 1.0,
      "source": "index_notlogin",
      "target": "global"
    },
    {
      "relation": "references",
      "confidence": "EXTRACTED",
      "confidence_score": 1.0,
      "source_file": "pages/lokasi/index.html",
      "source_location": null,
      "weight": 1.0,
      "source": "lokasi_index",
      "target": "global"
    },
    {
      "relation": "references",
      "confidence": "EXTRACTED",
      "confidence_score": 1.0,
      "source_file": "pages/notifikasi/index.html",
      "source_location": null,
      "weight": 1.0,
      "source": "notifikasi_index",
      "target": "global"
    },
    {
      "relation": "references",
      "confidence": "EXTRACTED",
      "confidence_score": 1.0,
      "source_file": "pages/pendaftaran/index.html",
      "source_location": null,
      "weight": 1.0,
      "source": "pendaftaran_index",
      "target": "global"
    },
    {
      "relation": "references",
      "confidence": "EXTRACTED",
      "confidence_score": 1.0,
      "source_file": "pages/pendaftaran/menghubungiServer.html",
      "source_location": null,
      "weight": 1.0,
      "source": "pendaftaran_menghubungiserver",
      "target": "global"
    },
    {
      "relation": "references",
      "confidence": "EXTRACTED",
      "confidence_score": 1.0,
      "source_file": "pages/profil/index.html",
      "source_location": null,
      "weight": 1.0,
      "source": "profil_index",
      "target": "global"
    },
    {
      "relation": "references",
      "confidence": "EXTRACTED",
      "confidence_score": 1.0,
      "source_file": "pages/rekam_medis/index.html",
      "source_location": null,
      "weight": 1.0,
      "source": "rekam_medis_index",
      "target": "global"
    },
    {
      "relation": "references",
      "confidence": "EXTRACTED",
      "confidence_score": 1.0,
      "source_file": "pages/pendaftaran/ticket/index.html",
      "source_location": null,
      "weight": 1.0,
      "source": "ticket_index",
      "target": "global"
    },
    {
      "relation": "references",
      "confidence": "EXTRACTED",
      "confidence_score": 1.0,
      "source_file": "pages/profil/verifikasiEmail/index.html",
      "source_location": null,
      "weight": 1.0,
      "source": "verifikasiemail_index",
      "target": "global"
    },
    {
      "relation": "references",
      "confidence": "EXTRACTED",
      "confidence_score": 1.0,
      "source_file": "pages/profil/verifikasiNomor/index.html",
      "source_location": null,
      "weight": 1.0,
      "source": "verifikasinomor_index",
      "target": "global"
    },
    {
      "relation": "references",
      "confidence": "EXTRACTED",
      "confidence_score": 1.0,
      "source_file": "pages/daftar_login/index.html",
      "source_location": null,
      "weight": 1.0,
      "source": "daftar_login_index",
      "target": "daftar_login_daftar"
    },
    {
      "relation": "references",
      "confidence": "EXTRACTED",
      "confidence_score": 1.0,
      "source_file": "pages/lokasi/index.html",
      "source_location": null,
      "weight": 1.0,
      "source": "lokasi_index",
      "target": "lokasi_index"
    },
    {
      "relation": "references",
      "confidence": "EXTRACTED",
      "confidence_score": 1.0,
      "source_file": "pages/lokasi/index.html",
      "source_location": null,
      "weight": 1.0,
      "source": "lokasi_index",
      "target": "pendaftaran_index"
    },
    {
      "relation": "references",
      "confidence": "EXTRACTED",
      "confidence_score": 1.0,
      "source_file": "pages/lokasi/index.html",
      "source_location": null,
      "weight": 1.0,
      "source": "lokasi_index",
      "target": "pendaftaran_pendaftaranpasienbaru"
    },
    {
      "relation": "references",
      "confidence": "EXTRACTED",
      "confidence_score": 1.0,
      "source_file": "pages/lokasi/index.html",
      "source_location": null,
      "weight": 1.0,
      "source": "lokasi_index",
      "target": "profil_index"
    },
    {
      "relation": "references",
      "confidence": "EXTRACTED",
      "confidence_score": 1.0,
      "source_file": "pages/lokasi/index.html",
      "source_location": null,
      "weight": 1.0,
      "source": "lokasi_index",
      "target": "rekam_medis_index"
    },
    {
      "relation": "references",
      "confidence": "EXTRACTED",
      "confidence_score": 1.0,
      "source_file": "pages/notifikasi/index.html",
      "source_location": null,
      "weight": 1.0,
      "source": "notifikasi_index",
      "target": "lokasi_index"
    },
    {
      "relation": "references",
      "confidence": "EXTRACTED",
      "confidence_score": 1.0,
      "source_file": "pages/pendaftaran/ticket/index.html",
      "source_location": null,
      "weight": 1.0,
      "source": "ticket_index",
      "target": "lokasi_index"
    },
    {
      "relation": "references",
      "confidence": "EXTRACTED",
      "confidence_score": 1.0,
      "source_file": "pages/profil/verifikasiEmail/index.html",
      "source_location": null,
      "weight": 1.0,
      "source": "verifikasiemail_index",
      "target": "lokasi_index"
    },
    {
      "relation": "references",
      "confidence": "EXTRACTED",
      "confidence_score": 1.0,
      "source_file": "pages/profil/verifikasiNomor/index.html",
      "source_location": null,
      "weight": 1.0,
      "source": "verifikasinomor_index",
      "target": "lokasi_index"
    },
    {
      "relation": "references",
      "confidence": "EXTRACTED",
      "confidence_score": 1.0,
      "source_file": "pages/pendaftaran/index.html",
      "source_location": null,
      "weight": 1.0,
      "source": "pendaftaran_index",
      "target": "pendaftaran_pendaftaranpasienbaru"
    },
    {
      "relation": "references",
      "confidence": "EXTRACTED",
      "confidence_score": 1.0,
      "source_file": "pages/pendaftaran/menghubungiServer.html",
      "source_location": null,
      "weight": 1.0,
      "source": "pendaftaran_menghubungiserver",
      "target": "pendaftaran_pendaftaranpasienbaru"
    },
    {
      "relation": "references",
      "confidence": "EXTRACTED",
      "confidence_score": 1.0,
      "source_file": "pages/profil/index.html",
      "source_location": null,
      "weight": 1.0,
      "source": "profil_index",
      "target": "pendaftaran_pendaftaranpasienbaru"
    },
    {
      "relation": "references",
      "confidence": "EXTRACTED",
      "confidence_score": 1.0,
      "source_file": "pages/rekam_medis/index.html",
      "source_location": null,
      "weight": 1.0,
      "source": "rekam_medis_index",
      "target": "pendaftaran_pendaftaranpasienbaru"
    },
    {
      "relation": "references",
      "confidence": "EXTRACTED",
      "confidence_score": 1.0,
      "source_file": "pages/pendaftaran/ticket/index.html",
      "source_location": null,
      "weight": 1.0,
      "source": "ticket_index",
      "target": "pendaftaran_pendaftaranpasienbaru"
    },
    {
      "relation": "references",
      "confidence": "EXTRACTED",
      "confidence_score": 1.0,
      "source_file": "pages/profil/verifikasiEmail/index.html",
      "source_location": null,
      "weight": 1.0,
      "source": "verifikasiemail_index",
      "target": "pendaftaran_pendaftaranpasienbaru"
    },
    {
      "relation": "references",
      "confidence": "EXTRACTED",
      "confidence_score": 1.0,
      "source_file": "pages/profil/verifikasiNomor/index.html",
      "source_location": null,
      "weight": 1.0,
      "source": "verifikasinomor_index",
      "target": "pendaftaran_pendaftaranpasienbaru"
    },
    {
      "relation": "references",
      "confidence": "EXTRACTED",
      "confidence_score": 1.0,
      "source_file": "pages/notifikasi/index.html",
      "source_location": null,
      "weight": 1.0,
      "source": "notifikasi_index",
      "target": "pendaftaran_index"
    },
    {
      "relation": "references",
      "confidence": "EXTRACTED",
      "confidence_score": 1.0,
      "source_file": "pages/notifikasi/index.html",
      "source_location": null,
      "weight": 1.0,
      "source": "notifikasi_index",
      "target": "profil_index"
    },
    {
      "relation": "references",
      "confidence": "EXTRACTED",
      "confidence_score": 1.0,
      "source_file": "pages/notifikasi/index.html",
      "source_location": null,
      "weight": 1.0,
      "source": "notifikasi_index",
      "target": "rekam_medis_index"
    },
    {
      "relation": "references",
      "confidence": "EXTRACTED",
      "confidence_score": 1.0,
      "source_file": "pages/pendaftaran/index.html",
      "source_location": null,
      "weight": 1.0,
      "source": "pendaftaran_index",
      "target": "pendaftaran_index"
    },
    {
      "relation": "references",
      "confidence": "EXTRACTED",
      "confidence_score": 1.0,
      "source_file": "pages/pendaftaran/index.html",
      "source_location": null,
      "weight": 1.0,
      "source": "pendaftaran_index",
      "target": "profil_index"
    },
    {
      "relation": "references",
      "confidence": "EXTRACTED",
      "confidence_score": 1.0,
      "source_file": "pages/pendaftaran/index.html",
      "source_location": null,
      "weight": 1.0,
      "source": "pendaftaran_index",
      "target": "rekam_medis_index"
    },
    {
      "relation": "references",
      "confidence": "EXTRACTED",
      "confidence_score": 1.0,
      "source_file": "pages/pendaftaran/ticket/index.html",
      "source_location": null,
      "weight": 1.0,
      "source": "ticket_index",
      "target": "pendaftaran_index"
    },
    {
      "relation": "references",
      "confidence": "EXTRACTED",
      "confidence_score": 1.0,
      "source_file": "pages/profil/verifikasiEmail/index.html",
      "source_location": null,
      "weight": 1.0,
      "source": "verifikasiemail_index",
      "target": "pendaftaran_index"
    },
    {
      "relation": "references",
      "confidence": "EXTRACTED",
      "confidence_score": 1.0,
      "source_file": "pages/profil/verifikasiNomor/index.html",
      "source_location": null,
      "weight": 1.0,
      "source": "verifikasinomor_index",
      "target": "pendaftaran_index"
    },
    {
      "relation": "references",
      "confidence": "EXTRACTED",
      "confidence_score": 1.0,
      "source_file": "pages/pendaftaran/ticket/index.html",
      "source_location": null,
      "weight": 1.0,
      "source": "ticket_index",
      "target": "profil_index"
    },
    {
      "relation": "references",
      "confidence": "EXTRACTED",
      "confidence_score": 1.0,
      "source_file": "pages/pendaftaran/ticket/index.html",
      "source_location": null,
      "weight": 1.0,
      "source": "ticket_index",
      "target": "rekam_medis_index"
    },
    {
      "relation": "references",
      "confidence": "EXTRACTED",
      "confidence_score": 1.0,
      "source_file": "pages/profil/index.html",
      "source_location": null,
      "weight": 1.0,
      "source": "profil_index",
      "target": "profil_index"
    },
    {
      "relation": "references",
      "confidence": "EXTRACTED",
      "confidence_score": 1.0,
      "source_file": "pages/profil/index.html",
      "source_location": null,
      "weight": 1.0,
      "source": "profil_index",
      "target": "profil_profil"
    },
    {
      "relation": "references",
      "confidence": "EXTRACTED",
      "confidence_score": 1.0,
      "source_file": "pages/profil/index.html",
      "source_location": null,
      "weight": 1.0,
      "source": "profil_index",
      "target": "rekam_medis_index"
    },
    {
      "relation": "references",
      "confidence": "EXTRACTED",
      "confidence_score": 1.0,
      "source_file": "pages/profil/index.html",
      "source_location": null,
      "weight": 1.0,
      "source": "profil_index",
      "target": "verifikasiemail_index"
    },
    {
      "relation": "references",
      "confidence": "EXTRACTED",
      "confidence_score": 1.0,
      "source_file": "pages/profil/index.html",
      "source_location": null,
      "weight": 1.0,
      "source": "profil_index",
      "target": "verifikasinomor_index"
    },
    {
      "relation": "references",
      "confidence": "EXTRACTED",
      "confidence_score": 1.0,
      "source_file": "pages/profil/verifikasiEmail/index.html",
      "source_location": null,
      "weight": 1.0,
      "source": "verifikasiemail_index",
      "target": "rekam_medis_index"
    },
    {
      "relation": "references",
      "confidence": "EXTRACTED",
      "confidence_score": 1.0,
      "source_file": "pages/profil/verifikasiNomor/index.html",
      "source_location": null,
      "weight": 1.0,
      "source": "verifikasinomor_index",
      "target": "rekam_medis_index"
    },
    {
      "relation": "references",
      "confidence": "EXTRACTED",
      "confidence_score": 1.0,
      "source_file": "pages/rekam_medis/index.html",
      "source_location": null,
      "weight": 1.0,
      "source": "rekam_medis_index",
      "target": "rekam_medis_index"
    },
    {
      "relation": "references",
      "confidence": "EXTRACTED",
      "confidence_score": 1.0,
      "source_file": "pages/rekam_medis/index.html",
      "source_location": null,
      "weight": 1.0,
      "source": "rekam_medis_index",
      "target": "rekam_medis_rekam_medis"
    }
  ],
  "hyperedges": [
    {
      "id": "patient_registration_flow",
      "label": "Patient Registration Flow",
      "nodes": [
        "pendaftaran_index",
        "pendaftaran_menghubungiserver",
        "ticket_index"
      ],
      "relation": "form",
      "confidence": "INFERRED",
      "confidence_score": 0.95,
      "source_file": "pages/pendaftaran/index.html"
    },
    {
      "id": "user_profile_verification_flow",
      "label": "User Profile Verification Flow",
      "nodes": [
        "profil_index",
        "verifikasiemail_index",
        "verifikasinomor_index"
      ],
      "relation": "form",
      "confidence": "INFERRED",
      "confidence_score": 0.95,
      "source_file": "pages/profil/index.html"
    }
  ],
  "built_at_commit": "bdfd660259fbb9807cad6198027a13b1ce2fcfc3"
}